{
  "version": "fee_base_inputs.v1",
  "generatedAt": "2026-03-15T13:49:25.915Z",
  "observedAt": "2026-03-15T13:49:25.915Z",
  "expiresAt": "2026-03-15T17:49:25.915Z",
  "freshnessStatus": "FRESH",
  "status": "ACTIVE",
  "reasonCode": null,
  "instructions": [],
  "periodSeconds": 604800,
  "policyVersionHash": "sha256:c84a48cc109277303c8b7858c979081b4b89b761930d4193f9d2e7a52277e240",
  "sourceRefs": {
    "economicsRef": "ops/runtime/vault-economics.latest.json",
    "feePolicyRef": "config/fees.policy.json",
    "canonicalRef": "config/canonical.vaults.json",
    "runtimeUniverseRef": "config/vault-lineup.v4.json",
    "aumSnapshotsRef": "ops/runtime/aum-snapshots.latest.json",
    "flowMetricsRef": "ops/runtime/flow-metrics.latest.json",
    "actionCapabilitiesRef": "ops/runtime/action-capabilities.latest.json",
    "sharePriceRef": "ops/runtime/share-price-snapshots.latest.json"
  },
  "totals": {
    "vaultsTotal": 8,
    "computableVaults": 8,
    "railModeCounts": {
      "settlementActive": 23,
      "disclosureOnly": 0,
      "notMeasured": 9
    }
  },
  "vaults": {
    "plasma_aave_usdt0": {
      "status": "ACTIVE",
      "reasonCode": null,
      "aumUsd": 5.00569,
      "volumeUsd": 0,
      "withdrawUsd": 0,
      "grossApyFraction": 0.02555106257,
      "periodSeconds": 604800,
      "railModes": {
        "mgmt": "NOT_MEASURED",
        "exec": "SETTLEMENT_ACTIVE",
        "perf": "NOT_MEASURED",
        "exit": "SETTLEMENT_ACTIVE"
      },
      "feeScheduleBps": {
        "mgmt": 0,
        "exec": 10,
        "perf": 0,
        "exit": 10
      },
      "howToFix": [],
      "requiredInputs": []
    },
    "plasma_stable_allocator_v2": {
      "status": "ACTIVE",
      "reasonCode": null,
      "aumUsd": 5.006771,
      "volumeUsd": 0,
      "withdrawUsd": 0,
      "grossApyFraction": 0.0424,
      "periodSeconds": 604800,
      "railModes": {
        "mgmt": "NOT_MEASURED",
        "exec": "SETTLEMENT_ACTIVE",
        "perf": "SETTLEMENT_ACTIVE",
        "exit": "SETTLEMENT_ACTIVE"
      },
      "feeScheduleBps": {
        "mgmt": 0,
        "exec": 10,
        "perf": 1000,
        "exit": 10
      },
      "howToFix": [],
      "requiredInputs": []
    },
    "plasma_pt_usde": {
      "status": "ACTIVE",
      "reasonCode": null,
      "aumUsd": 6.563943,
      "volumeUsd": 0,
      "withdrawUsd": 0,
      "grossApyFraction": 0.034083280758,
      "periodSeconds": 604800,
      "railModes": {
        "mgmt": "NOT_MEASURED",
        "exec": "SETTLEMENT_ACTIVE",
        "perf": "SETTLEMENT_ACTIVE",
        "exit": "SETTLEMENT_ACTIVE"
      },
      "feeScheduleBps": {
        "mgmt": 0,
        "exec": 10,
        "perf": 1000,
        "exit": 10
      },
      "howToFix": [],
      "requiredInputs": []
    },
    "plasma_pt_susde": {
      "status": "ACTIVE",
      "reasonCode": null,
      "aumUsd": 5.347069,
      "volumeUsd": 0,
      "withdrawUsd": 0,
      "grossApyFraction": 0.04001256623,
      "periodSeconds": 604800,
      "railModes": {
        "mgmt": "NOT_MEASURED",
        "exec": "SETTLEMENT_ACTIVE",
        "perf": "SETTLEMENT_ACTIVE",
        "exit": "SETTLEMENT_ACTIVE"
      },
      "feeScheduleBps": {
        "mgmt": 0,
        "exec": 10,
        "perf": 1000,
        "exit": 10
      },
      "howToFix": [],
      "requiredInputs": []
    },
    "plasma_pt_syrup": {
      "status": "ACTIVE",
      "reasonCode": null,
      "aumUsd": 6.852584,
      "volumeUsd": 0,
      "withdrawUsd": 0,
      "grossApyFraction": 0.045806062293,
      "periodSeconds": 604800,
      "railModes": {
        "mgmt": "NOT_MEASURED",
        "exec": "SETTLEMENT_ACTIVE",
        "perf": "SETTLEMENT_ACTIVE",
        "exit": "SETTLEMENT_ACTIVE"
      },
      "feeScheduleBps": {
        "mgmt": 0,
        "exec": 10,
        "perf": 1000,
        "exit": 10
      },
      "howToFix": [],
      "requiredInputs": []
    },
    "plasma_pt_usdai": {
      "status": "ACTIVE",
      "reasonCode": null,
      "aumUsd": 6.44347,
      "volumeUsd": 0,
      "withdrawUsd": 0,
      "grossApyFraction": 0.111271851835,
      "periodSeconds": 604800,
      "railModes": {
        "mgmt": "NOT_MEASURED",
        "exec": "SETTLEMENT_ACTIVE",
        "perf": "SETTLEMENT_ACTIVE",
        "exit": "SETTLEMENT_ACTIVE"
      },
      "feeScheduleBps": {
        "mgmt": 0,
        "exec": 10,
        "perf": 1000,
        "exit": 10
      },
      "howToFix": [],
      "requiredInputs": []
    },
    "plasma_fluid_susdai_recursive_carry": {
      "status": "ACTIVE",
      "reasonCode": null,
      "aumUsd": 4.9187,
      "volumeUsd": 0,
      "withdrawUsd": 0,
      "grossApyFraction": 0.132021359113,
      "periodSeconds": 604800,
      "railModes": {
        "mgmt": "NOT_MEASURED",
        "exec": "SETTLEMENT_ACTIVE",
        "perf": "SETTLEMENT_ACTIVE",
        "exit": "SETTLEMENT_ACTIVE"
      },
      "feeScheduleBps": {
        "mgmt": 0,
        "exec": 10,
        "perf": 1200,
        "exit": 10
      },
      "howToFix": [],
      "requiredInputs": []
    },
    "plasma_fluid_weeth_recursive_carry": {
      "status": "ACTIVE",
      "reasonCode": null,
      "aumUsd": 3.25793,
      "volumeUsd": 0,
      "withdrawUsd": 0,
      "grossApyFraction": 0.053,
      "periodSeconds": 604800,
      "railModes": {
        "mgmt": "NOT_MEASURED",
        "exec": "SETTLEMENT_ACTIVE",
        "perf": "SETTLEMENT_ACTIVE",
        "exit": "SETTLEMENT_ACTIVE"
      },
      "feeScheduleBps": {
        "mgmt": 0,
        "exec": 10,
        "perf": 1500,
        "exit": 10
      },
      "howToFix": [],
      "requiredInputs": []
    }
  }
}
