{
  "version": "observation_sweep_automation.v1",
  "asOfTimestamp": "2026-03-18T05:04:21.931Z",
  "tag": "ci-obs-23229941693",
  "rpcMode": "ci",
  "status": "NOOP",
  "reasonCode": "FRESH",
  "note": "State is not stale yet. Use --force to bypass.",
  "startArtifactMode": "existing",
  "policy": {
    "headlineWindowDays": 7,
    "secondaryWindowsDays": [
      30
    ]
  },
  "lanes": {
    "plasma_pendle_yt_syrupusdt_volatility": {
      "observationCount": 2,
      "windowDays": 1.0242,
      "annualizedEligible": false
    },
    "plasma_flow_engine_pendle_lp_susde": {
      "observationCount": 2,
      "windowDays": 1.0242,
      "annualizedEligible": false
    },
    "plasma_delta_fee_engine_pendle_lp_usde": {
      "observationCount": 2,
      "windowDays": 1.0242,
      "annualizedEligible": false
    }
  },
  "staleBefore": false,
  "staleAfter": false,
  "checksum": "sha256:b89d95f83ded251ddaa4635876afa93422650baf8f1d71245a9141fc15adae7d"
}
