{
  "version": "rpc_health_v1",
  "tag": "ci-obs-23092356466",
  "generatedAt": "2026-03-14T17:03:19.028Z",
  "chainId": 9745,
  "endpoints": [
    {
      "label": "primary_env",
      "priority": 0,
      "status": "GREEN",
      "latestBlock": 16576040,
      "avgLatencyMs": 269,
      "successRate": 1,
      "reasons": []
    },
    {
      "label": "public_fallback",
      "priority": 1,
      "status": "GREEN",
      "latestBlock": 16576040,
      "avgLatencyMs": 234,
      "successRate": 1,
      "reasons": []
    }
  ],
  "rpcUsed": "https://rpc.plasma.to",
  "status": "GREEN",
  "failClosed": false,
  "instructions": null
}
